enzymetk/__init__.py
enzymetk/annotateEC_CLEAN_step.py
enzymetk/annotateEC_CREEP_step.py
enzymetk/annotateEC_proteinfer_step.py
enzymetk/dock_boltz_step.py
enzymetk/dock_chai_step.py
enzymetk/dock_vina_step.py
enzymetk/embedchem_chemberta_step.py
enzymetk/embedchem_rxnfp_run.py
enzymetk/embedchem_rxnfp_step.py
enzymetk/embedchem_selformer_run.py
enzymetk/embedchem_selformer_step.py
enzymetk/embedchem_unimol_step.py
enzymetk/embedprotein_esm3_step.py
enzymetk/embedprotein_esm_step.py
enzymetk/esm-extract.py
enzymetk/filter_sequence_step.py
enzymetk/filter_structure_step.py
enzymetk/generate_msa_step.py
enzymetk/generate_oligopool_step.py
enzymetk/generate_tree_step.py
enzymetk/inpaint_ligandMPNN_step.py
enzymetk/main.py
enzymetk/metagenomics_porechop_trim_reads_step.py
enzymetk/metagenomics_prokka_annotate_genes.py
enzymetk/pipeline.py
enzymetk/predict_activity_step.py
enzymetk/predict_catalyticsite_run.py
enzymetk/predict_catalyticsite_step.py
enzymetk/reducedim_pca_run.py
enzymetk/reducedim_vae_run.py
enzymetk/reducedim_vae_step.py
enzymetk/save_step.py
enzymetk/sequence_search_blast.py
enzymetk/similarity_foldseek_step.py
enzymetk/similarity_mmseqs_step.py
enzymetk/similarity_reaction_step.py
enzymetk/similarity_substrate_step.py
enzymetk/step.py
enzymetk-0.0.6.data/data/LICENSE
enzymetk-0.0.6.dist-info/licenses/LICENSE
enzymetk-0.0.6.dist-info/METADATA
enzymetk-0.0.6.dist-info/WHEEL
enzymetk-0.0.6.dist-info/entry_points.txt
enzymetk-0.0.6.dist-info/top_level.txt
enzymetk-0.0.6.dist-info/RECORD
