Metadata-Version: 2.4
Name: enzymetk
Version: 0.0.6
Home-page: https://github.com/arianemora/enzyme-tk/
Author: Ariane Mora
Author-email: ariane.n.mora@gmail.com
License: GPL3
Project-URL: Bug Tracker, https://github.com/arianemora/enzyme-tk/
Project-URL: Documentation, https://github.com/arianemora/enzyme-tk/
Project-URL: Source Code, https://github.com/arianemora/enzyme-tk/
Keywords: enzymes,protein-engineering
Classifier: Intended Audience :: Science/Research
Classifier: License :: OSI Approved :: GNU General Public License v3 (GPLv3)
Classifier: Natural Language :: English
Classifier: Operating System :: OS Independent
Classifier: Programming Language :: Python :: 3.8
Classifier: Topic :: Scientific/Engineering :: Bio-Informatics
Requires-Python: >=3.8
License-File: LICENSE
Requires-Dist: scikit-learn
Requires-Dist: numpy
Requires-Dist: seaborn
Requires-Dist: sciutil
Requires-Dist: pandas
Requires-Dist: biopython
Dynamic: author
Dynamic: author-email
Dynamic: classifier
Dynamic: description
Dynamic: description-content-type
Dynamic: home-page
Dynamic: keywords
Dynamic: license
Dynamic: license-file
Dynamic: project-url
Dynamic: requires-dist
Dynamic: requires-python
